{
    "1682007729871917:11966": {
        "IResourceController": {
            "public": {
                "path": "../AdditionalFiles/paz_dance_experiment_07 2/Materials"
            }
        }
    },
    "1682007729872416:12430": {
        "IResourceController": {
            "name": "Materials",
            "type": 0,
            "subtype": -1,
            "dependency": 0,
            "hidden": false,
            "publicId": "1682007729871917:11966",
            "resources": [
                "1682007729870781:10639"
            ]
        }
    }
}
