{
    "1682007729871915:11957": {
        "IResourceController": {
            "public": {
                "path": "paz_dance_experiment_07/Materials"
            }
        }
    },
    "1682007729872347:12422": {
        "IResourceController": {
            "name": "Materials",
            "type": 0,
            "subtype": -1,
            "dependency": 0,
            "hidden": false,
            "publicId": "1682007729871915:11957",
            "resources": [
                "1682007729870766:10510"
            ]
        }
    }
}
